{"statuses": [{"created_at": "Mon Feb 24 15:44:38 +0000 2020", "id": 1231968185655496704, "id_str": "1231968185655496704", "full_text": "RT @anyrun_app: TOP10 last week's threats by uploads\n\n⬇️ #Emotet 255 (270)\n⬆️ #LokiBot 235 (211)\n⬇️ #AgentTesla 167 (325)\n⬇️ #FormBook 125…", "truncated": false, "display_text_range": [0, 139], "entities": {"hashtags": [{"text": "Emotet", "indices": [57, 64]}, {"text": "LokiBot", "indices": [78, 86]}, {"text": "AgentTesla", "indices": [100, 111]}, {"text": "FormBook", "indices": [125, 134]}], "symbols": [], "user_mentions": [{"screen_name": "anyrun_app", "name": "ANY.RUN", "id": 833639043862786048, "id_str": "833639043862786048", "indices": [3, 14]}], "urls": []}, "metadata": {"iso_language_code": "en", "result_type": "recent"}, "source": "<a href=\"http://twitter.com/download/android\" rel=\"nofollow\">Twitter for Android</a>", "in_reply_to_status_id": null, "in_reply_to_status_id_str": null, "in_reply_to_user_id": null, "in_reply_to_user_id_str": null, "in_reply_to_screen_name": null, "user": {"id": 2906179109, "id_str": "2906179109", "name": "MalwareDev", "screen_name": "Malwaredev", "location": "", "description": "The Battle Against Malwares & Hackers. Private Account.\nAll opinions expressed here are mine only.", "url": "https://t.co/UGqwJZmVNM", "entities": {"url": {"urls": [{"url": "https://t.co/UGqwJZmVNM", "expanded_url": "http://malwarebattle.blogspot.com/", "display_url": "malwarebattle.blogspot.com", "indices": [0, 23]}]}, "description": {"urls": []}}, "protected": false, "followers_count": 1405, "friends_count": 1702, "listed_count": 108, "created_at": "Fri Dec 05 09:57:13 +0000 2014", "favourites_count": 12887, "utc_offset": null, "time_zone": null, "geo_enabled": false, "verified": false, "statuses_count": 27868, "lang": null, "contributors_enabled": false, "is_translator": false, "is_translation_enabled": false, "profile_background_color": "000000", "profile_background_image_url": "http://abs.twimg.com/images/themes/theme1/bg.png", "profile_background_image_url_https": "https://abs.twimg.com/images/themes/theme1/bg.png", "profile_background_tile": false, "profile_image_url": "http://pbs.twimg.com/profile_images/540807592826519552/2EzzHkJq_normal.png", "profile_image_url_https": "https://pbs.twimg.com/profile_images/540807592826519552/2EzzHkJq_normal.png", "profile_banner_url": "https://pbs.twimg.com/profile_banners/2906179109/1417775102", "profile_link_color": "3B94D9", "profile_sidebar_border_color": "000000", "profile_sidebar_fill_color": "000000", "profile_text_color": "000000", "profile_use_background_image": false, "has_extended_profile": false, "default_profile": false, "default_profile_image": false, "following": false, "follow_request_sent": false, "notifications": false, "translator_type": "none"}, "geo": null, "coordinates": null, "place": null, "contributors": null, "retweeted_status": {"created_at": "Mon Feb 24 06:04:45 +0000 2020", "id": 1231822251382788096, "id_str": "1231822251382788096", "full_text": "TOP10 last week's threats by uploads\n\n⬇️ #Emotet 255 (270)\n⬆️ #LokiBot 235 (211)\n⬇️ #AgentTesla 167 (325)\n⬇️ #FormBook 125 (141)\n⬇️ #NanoCore 116 (168)\n⬆️ #Remcos 82 (66)\n⬇️ #Ursnif 81 (94)\n⬇️ #HawkEye 73 (148)\n⬇️ #AZORult 57 (95)\n⬆️ #Pyrogenic 53 (5)\n\nhttps://t.co/98nRpXOxWw", "truncated": false, "display_text_range": [0, 276], "entities": {"hashtags": [{"text": "Emotet", "indices": [41, 48]}, {"text": "LokiBot", "indices": [62, 70]}, {"text": "AgentTesla", "indices": [84, 95]}, {"text": "FormBook", "indices": [109, 118]}, {"text": "NanoCore", "indices": [132, 141]}, {"text": "Remcos", "indices": [155, 162]}, {"text": "Ursnif", "indices": [174, 181]}, {"text": "HawkEye", "indices": [193, 201]}, {"text": "AZORult", "indices": [214, 222]}, {"text": "Pyrogenic", "indices": [234, 244]}], "symbols": [], "user_mentions": [], "urls": [{"url": "https://t.co/98nRpXOxWw", "expanded_url": "https://any.run/malware-trends/", "display_url": "any.run/malware-trends/", "indices": [253, 276]}]}, "metadata": {"iso_language_code": "en", "result_type": "recent"}, "source": "<a href=\"https://mobile.twitter.com\" rel=\"nofollow\">Twitter Web App</a>", "in_reply_to_status_id": null, "in_reply_to_status_id_str": null, "in_reply_to_user_id": null, "in_reply_to_user_id_str": null, "in_reply_to_screen_name": null, "user": {"id": 833639043862786048, "id_str": "833639043862786048", "name": "ANY.RUN", "screen_name": "anyrun_app", "location": "", "description": "Interactive #malware analysis service. Useful for dynamic research of most types of #cyberthreats using any environments.", "url": "https://t.co/ksXUw2hK1m", "entities": {"url": {"urls": [{"url": "https://t.co/ksXUw2hK1m", "expanded_url": "https://www.any.run/", "display_url": "any.run", "indices": [0, 23]}]}, "description": {"urls": []}}, "protected": false, "followers_count": 10499, "friends_count": 175, "listed_count": 188, "created_at": "Mon Feb 20 11:26:51 +0000 2017", "favourites_count": 2359, "utc_offset": null, "time_zone": null, "geo_enabled": false, "verified": false, "statuses_count": 1131, "lang": null, "contributors_enabled": false, "is_translator": false, "is_translation_enabled": false, "profile_background_color": "000000", "profile_background_image_url": "http://abs.twimg.com/images/themes/theme1/bg.png", "profile_background_image_url_https": "https://abs.twimg.com/images/themes/theme1/bg.png", "profile_background_tile": false, "profile_image_url": "http://pbs.twimg.com/profile_images/888000026437447681/upTlRuwp_normal.jpg", "profile_image_url_https": "https://pbs.twimg.com/profile_images/888000026437447681/upTlRuwp_normal.jpg", "profile_banner_url": "https://pbs.twimg.com/profile_banners/833639043862786048/1518700753", "profile_link_color": "377C9D", "profile_sidebar_border_color": "000000", "profile_sidebar_fill_color": "000000", "profile_text_color": "000000", "profile_use_background_image": false, "has_extended_profile": false, "default_profile": false, "default_profile_image": false, "following": false, "follow_request_sent": false, "notifications": false, "translator_type": "none"}, "geo": null, "coordinates": null, "place": null, "contributors": null, "is_quote_status": false, "retweet_count": 7, "favorite_count": 12, "favorited": false, "retweeted": false, "possibly_sensitive": false, "lang": "en"}, "is_quote_status": false, "retweet_count": 7, "favorite_count": 0, "favorited": false, "retweeted": false, "possibly_sensitive": false, "lang": "en"}, {"created_at": "Mon Feb 24 14:41:22 +0000 2020", "id": 1231952262953607170, "id_str": "1231952262953607170", "full_text": "RT @anyrun_app: TOP10 last week's threats by uploads\n\n⬇️ #Emotet 255 (270)\n⬆️ #LokiBot 235 (211)\n⬇️ #AgentTesla 167 (325)\n⬇️ #FormBook 125…", "truncated": false, "display_text_range": [0, 139], "entities": {"hashtags": [{"text": "Emotet", "indices": [57, 64]}, {"text": "LokiBot", "indices": [78, 86]}, {"text": "AgentTesla", "indices": [100, 111]}, {"text": "FormBook", "indices": [125, 134]}], "symbols": [], "user_mentions": [{"screen_name": "anyrun_app", "name": "ANY.RUN", "id": 833639043862786048, "id_str": "833639043862786048", "indices": [3, 14]}], "urls": []}, "metadata": {"iso_language_code": "en", "result_type": "recent"}, "source": "<a href=\"http://twitter.com/download/android\" rel=\"nofollow\">Twitter for Android</a>", "in_reply_to_status_id": null, "in_reply_to_status_id_str": null, "in_reply_to_user_id": null, "in_reply_to_user_id_str": null, "in_reply_to_screen_name": null, "user": {"id": 1091099604744105990, "id_str": "1091099604744105990", "name": "cog", "screen_name": "Jason_DFIR", "location": "Toronto, Ontario", "description": "", "url": null, "entities": {"description": {"urls": []}}, "protected": false, "followers_count": 18, "friends_count": 119, "listed_count": 0, "created_at": "Thu Jan 31 22:23:12 +0000 2019", "favourites_count": 535, "utc_offset": null, "time_zone": null, "geo_enabled": false, "verified": false, "statuses_count": 261, "lang": null, "contributors_enabled": false, "is_translator": false, "is_translation_enabled": false, "profile_background_color": "000000", "profile_background_image_url": "http://abs.twimg.com/images/themes/theme1/bg.png", "profile_background_image_url_https": "https://abs.twimg.com/images/themes/theme1/bg.png", "profile_background_tile": false, "profile_image_url": "http://pbs.twimg.com/profile_images/1107830299621314560/RZStdgJW_normal.jpg", "profile_image_url_https": "https://pbs.twimg.com/profile_images/1107830299621314560/RZStdgJW_normal.jpg", "profile_link_color": "ABB8C2", "profile_sidebar_border_color": "000000", "profile_sidebar_fill_color": "000000", "profile_text_color": "000000", "profile_use_background_image": false, "has_extended_profile": false, "default_profile": false, "default_profile_image": false, "following": false, "follow_request_sent": false, "notifications": false, "translator_type": "none"}, "geo": null, "coordinates": null, "place": null, "contributors": null, "retweeted_status": {"created_at": "Mon Feb 24 06:04:45 +0000 2020", "id": 1231822251382788096, "id_str": "1231822251382788096", "full_text": "TOP10 last week's threats by uploads\n\n⬇️ #Emotet 255 (270)\n⬆️ #LokiBot 235 (211)\n⬇️ #AgentTesla 167 (325)\n⬇️ #FormBook 125 (141)\n⬇️ #NanoCore 116 (168)\n⬆️ #Remcos 82 (66)\n⬇️ #Ursnif 81 (94)\n⬇️ #HawkEye 73 (148)\n⬇️ #AZORult 57 (95)\n⬆️ #Pyrogenic 53 (5)\n\nhttps://t.co/98nRpXOxWw", "truncated": false, "display_text_range": [0, 276], "entities": {"hashtags": [{"text": "Emotet", "indices": [41, 48]}, {"text": "LokiBot", "indices": [62, 70]}, {"text": "AgentTesla", "indices": [84, 95]}, {"text": "FormBook", "indices": [109, 118]}, {"text": "NanoCore", "indices": [132, 141]}, {"text": "Remcos", "indices": [155, 162]}, {"text": "Ursnif", "indices": [174, 181]}, {"text": "HawkEye", "indices": [193, 201]}, {"text": "AZORult", "indices": [214, 222]}, {"text": "Pyrogenic", "indices": [234, 244]}], "symbols": [], "user_mentions": [], "urls": [{"url": "https://t.co/98nRpXOxWw", "expanded_url": "https://any.run/malware-trends/", "display_url": "any.run/malware-trends/", "indices": [253, 276]}]}, "metadata": {"iso_language_code": "en", "result_type": "recent"}, "source": "<a href=\"https://mobile.twitter.com\" rel=\"nofollow\">Twitter Web App</a>", "in_reply_to_status_id": null, "in_reply_to_status_id_str": null, "in_reply_to_user_id": null, "in_reply_to_user_id_str": null, "in_reply_to_screen_name": null, "user": {"id": 833639043862786048, "id_str": "833639043862786048", "name": "ANY.RUN", "screen_name": "anyrun_app", "location": "", "description": "Interactive #malware analysis service. Useful for dynamic research of most types of #cyberthreats using any environments.", "url": "https://t.co/ksXUw2hK1m", "entities": {"url": {"urls": [{"url": "https://t.co/ksXUw2hK1m", "expanded_url": "https://www.any.run/", "display_url": "any.run", "indices": [0, 23]}]}, "description": {"urls": []}}, "protected": false, "followers_count": 10499, "friends_count": 175, "listed_count": 188, "created_at": "Mon Feb 20 11:26:51 +0000 2017", "favourites_count": 2359, "utc_offset": null, "time_zone": null, "geo_enabled": false, "verified": false, "statuses_count": 1131, "lang": null, "contributors_enabled": false, "is_translator": false, "is_translation_enabled": false, "profile_background_color": "000000", "profile_background_image_url": "http://abs.twimg.com/images/themes/theme1/bg.png", "profile_background_image_url_https": "https://abs.twimg.com/images/themes/theme1/bg.png", "profile_background_tile": false, "profile_image_url": "http://pbs.twimg.com/profile_images/888000026437447681/upTlRuwp_normal.jpg", "profile_image_url_https": "https://pbs.twimg.com/profile_images/888000026437447681/upTlRuwp_normal.jpg", "profile_banner_url": "https://pbs.twimg.com/profile_banners/833639043862786048/1518700753", "profile_link_color": "377C9D", "profile_sidebar_border_color": "000000", "profile_sidebar_fill_color": "000000", "profile_text_color": "000000", "profile_use_background_image": false, "has_extended_profile": false, "default_profile": false, "default_profile_image": false, "following": false, "follow_request_sent": false, "notifications": false, "translator_type": "none"}, "geo": null, "coordinates": null, "place": null, "contributors": null, "is_quote_status": false, "retweet_count": 7, "favorite_count": 12, "favorited": false, "retweeted": false, "possibly_sensitive": false, "lang": "en"}, "is_quote_status": false, "retweet_count": 7, "favorite_count": 0, "favorited": false, "retweeted": false, "possibly_sensitive": false, "lang": "en"}, {"created_at": "Mon Feb 24 12:13:53 +0000 2020", "id": 1231915145028362240, "id_str": "1231915145028362240", "full_text": "RT @anyrun_app: TOP10 last week's threats by uploads\n\n⬇️ #Emotet 255 (270)\n⬆️ #LokiBot 235 (211)\n⬇️ #AgentTesla 167 (325)\n⬇️ #FormBook 125…", "truncated": false, "display_text_range": [0, 139], "entities": {"hashtags": [{"text": "Emotet", "indices": [57, 64]}, {"text": "LokiBot", "indices": [78, 86]}, {"text": "AgentTesla", "indices": [100, 111]}, {"text": "FormBook", "indices": [125, 134]}], "symbols": [], "user_mentions": [{"screen_name": "anyrun_app", "name": "ANY.RUN", "id": 833639043862786048, "id_str": "833639043862786048", "indices": [3, 14]}], "urls": []}, "metadata": {"iso_language_code": "en", "result_type": "recent"}, "source": "<a href=\"http://twitter.com/download/android\" rel=\"nofollow\">Twitter for Android</a>", "in_reply_to_status_id": null, "in_reply_to_status_id_str": null, "in_reply_to_user_id": null, "in_reply_to_user_id_str": null, "in_reply_to_screen_name": null, "user": {"id": 1029034638612852736, "id_str": "1029034638612852736", "name": "3-Eyed Raven", "screen_name": "3E_Raven", "location": "", "description": "", "url": null, "entities": {"description": {"urls": []}}, "protected": false, "followers_count": 25, "friends_count": 198, "listed_count": 3, "created_at": "Mon Aug 13 15:59:11 +0000 2018", "favourites_count": 9, "utc_offset": null, "time_zone": null, "geo_enabled": false, "verified": false, "statuses_count": 1396, "lang": null, "contributors_enabled": false, "is_translator": false, "is_translation_enabled": false, "profile_background_color": "000000", "profile_background_image_url": "http://abs.twimg.com/images/themes/theme1/bg.png", "profile_background_image_url_https": "https://abs.twimg.com/images/themes/theme1/bg.png", "profile_background_tile": false, "profile_image_url": "http://pbs.twimg.com/profile_images/1222634793327910912/mKpp5mIO_normal.jpg", "profile_image_url_https": "https://pbs.twimg.com/profile_images/1222634793327910912/mKpp5mIO_normal.jpg", "profile_link_color": "91D2FA", "profile_sidebar_border_color": "000000", "profile_sidebar_fill_color": "000000", "profile_text_color": "000000", "profile_use_background_image": false, "has_extended_profile": false, "default_profile": false, "default_profile_image": false, "following": false, "follow_request_sent": false, "notifications": false, "translator_type": "none"}, "geo": null, "coordinates": null, "place": null, "contributors": null, "retweeted_status": {"created_at": "Mon Feb 24 06:04:45 +0000 2020", "id": 1231822251382788096, "id_str": "1231822251382788096", "full_text": "TOP10 last week's threats by uploads\n\n⬇️ #Emotet 255 (270)\n⬆️ #LokiBot 235 (211)\n⬇️ #AgentTesla 167 (325)\n⬇️ #FormBook 125 (141)\n⬇️ #NanoCore 116 (168)\n⬆️ #Remcos 82 (66)\n⬇️ #Ursnif 81 (94)\n⬇️ #HawkEye 73 (148)\n⬇️ #AZORult 57 (95)\n⬆️ #Pyrogenic 53 (5)\n\nhttps://t.co/98nRpXOxWw", "truncated": false, "display_text_range": [0, 276], "entities": {"hashtags": [{"text": "Emotet", "indices": [41, 48]}, {"text": "LokiBot", "indices": [62, 70]}, {"text": "AgentTesla", "indices": [84, 95]}, {"text": "FormBook", "indices": [109, 118]}, {"text": "NanoCore", "indices": [132, 141]}, {"text": "Remcos", "indices": [155, 162]}, {"text": "Ursnif", "indices": [174, 181]}, {"text": "HawkEye", "indices": [193, 201]}, {"text": "AZORult", "indices": [214, 222]}, {"text": "Pyrogenic", "indices": [234, 244]}], "symbols": [], "user_mentions": [], "urls": [{"url": "https://t.co/98nRpXOxWw", "expanded_url": "https://any.run/malware-trends/", "display_url": "any.run/malware-trends/", "indices": [253, 276]}]}, "metadata": {"iso_language_code": "en", "result_type": "recent"}, "source": "<a href=\"https://mobile.twitter.com\" rel=\"nofollow\">Twitter Web App</a>", "in_reply_to_status_id": null, "in_reply_to_status_id_str": null, "in_reply_to_user_id": null, "in_reply_to_user_id_str": null, "in_reply_to_screen_name": null, "user": {"id": 833639043862786048, "id_str": "833639043862786048", "name": "ANY.RUN", "screen_name": "anyrun_app", "location": "", "description": "Interactive #malware analysis service. Useful for dynamic research of most types of #cyberthreats using any environments.", "url": "https://t.co/ksXUw2hK1m", "entities": {"url": {"urls": [{"url": "https://t.co/ksXUw2hK1m", "expanded_url": "https://www.any.run/", "display_url": "any.run", "indices": [0, 23]}]}, "description": {"urls": []}}, "protected": false, "followers_count": 10499, "friends_count": 175, "listed_count": 188, "created_at": "Mon Feb 20 11:26:51 +0000 2017", "favourites_count": 2359, "utc_offset": null, "time_zone": null, "geo_enabled": false, "verified": false, "statuses_count": 1131, "lang": null, "contributors_enabled": false, "is_translator": false, "is_translation_enabled": false, "profile_background_color": "000000", "profile_background_image_url": "http://abs.twimg.com/images/themes/theme1/bg.png", "profile_background_image_url_https": "https://abs.twimg.com/images/themes/theme1/bg.png", "profile_background_tile": false, "profile_image_url": "http://pbs.twimg.com/profile_images/888000026437447681/upTlRuwp_normal.jpg", "profile_image_url_https": "https://pbs.twimg.com/profile_images/888000026437447681/upTlRuwp_normal.jpg", "profile_banner_url": "https://pbs.twimg.com/profile_banners/833639043862786048/1518700753", "profile_link_color": "377C9D", "profile_sidebar_border_color": "000000", "profile_sidebar_fill_color": "000000", "profile_text_color": "000000", "profile_use_background_image": false, "has_extended_profile": false, "default_profile": false, "default_profile_image": false, "following": false, "follow_request_sent": false, "notifications": false, "translator_type": "none"}, "geo": null, "coordinates": null, "place": null, "contributors": null, "is_quote_status": false, "retweet_count": 7, "favorite_count": 12, "favorited": false, "retweeted": false, "possibly_sensitive": false, "lang": "en"}, "is_quote_status": false, "retweet_count": 7, "favorite_count": 0, "favorited": false, "retweeted": false, "possibly_sensitive": false, "lang": "en"}, {"created_at": "Mon Feb 24 08:39:20 +0000 2020", "id": 1231861155049693184, "id_str": "1231861155049693184", "full_text": "RT @anyrun_app: TOP10 last week's threats by uploads\n\n⬇️ #Emotet 255 (270)\n⬆️ #LokiBot 235 (211)\n⬇️ #AgentTesla 167 (325)\n⬇️ #FormBook 125…", "truncated": false, "display_text_range": [0, 139], "entities": {"hashtags": [{"text": "Emotet", "indices": [57, 64]}, {"text": "LokiBot", "indices": [78, 86]}, {"text": "AgentTesla", "indices": [100, 111]}, {"text": "FormBook", "indices": [125, 134]}], "symbols": [], "user_mentions": [{"screen_name": "anyrun_app", "name": "ANY.RUN", "id": 833639043862786048, "id_str": "833639043862786048", "indices": [3, 14]}], "urls": []}, "metadata": {"iso_language_code": "en", "result_type": "recent"}, "source": "<a href=\"http://twitter.com/download/android\" rel=\"nofollow\">Twitter for Android</a>", "in_reply_to_status_id": null, "in_reply_to_status_id_str": null, "in_reply_to_user_id": null, "in_reply_to_user_id_str": null, "in_reply_to_screen_name": null, "user": {"id": 2653305134, "id_str": "2653305134", "name": "gh0std4ncer", "screen_name": "gh0std4ncer", "location": "", "description": "I came,I saw, I stuck around", "url": null, "entities": {"description": {"urls": []}}, "protected": false, "followers_count": 320, "friends_count": 223, "listed_count": 277, "created_at": "Thu Jul 17 09:29:17 +0000 2014", "favourites_count": 40083, "utc_offset": null, "time_zone": null, "geo_enabled": false, "verified": false, "statuses_count": 25858, "lang": null, "contributors_enabled": false, "is_translator": false, "is_translation_enabled": true, "profile_background_color": "C0DEED", "profile_background_image_url": "http://abs.twimg.com/images/themes/theme1/bg.png", "profile_background_image_url_https": "https://abs.twimg.com/images/themes/theme1/bg.png", "profile_background_tile": false, "profile_image_url": "http://pbs.twimg.com/profile_images/489755296374325248/1HPWwAdO_normal.jpeg", "profile_image_url_https": "https://pbs.twimg.com/profile_images/489755296374325248/1HPWwAdO_normal.jpeg", "profile_banner_url": "https://pbs.twimg.com/profile_banners/2653305134/1405601950", "profile_link_color": "1DA1F2", "profile_sidebar_border_color": "C0DEED", "profile_sidebar_fill_color": "DDEEF6", "profile_text_color": "333333", "profile_use_background_image": true, "has_extended_profile": false, "default_profile": true, "default_profile_image": false, "following": false, "follow_request_sent": false, "notifications": false, "translator_type": "none"}, "geo": null, "coordinates": null, "place": null, "contributors": null, "retweeted_status": {"created_at": "Mon Feb 24 06:04:45 +0000 2020", "id": 1231822251382788096, "id_str": "1231822251382788096", "full_text": "TOP10 last week's threats by uploads\n\n⬇️ #Emotet 255 (270)\n⬆️ #LokiBot 235 (211)\n⬇️ #AgentTesla 167 (325)\n⬇️ #FormBook 125 (141)\n⬇️ #NanoCore 116 (168)\n⬆️ #Remcos 82 (66)\n⬇️ #Ursnif 81 (94)\n⬇️ #HawkEye 73 (148)\n⬇️ #AZORult 57 (95)\n⬆️ #Pyrogenic 53 (5)\n\nhttps://t.co/98nRpXOxWw", "truncated": false, "display_text_range": [0, 276], "entities": {"hashtags": [{"text": "Emotet", "indices": [41, 48]}, {"text": "LokiBot", "indices": [62, 70]}, {"text": "AgentTesla", "indices": [84, 95]}, {"text": "FormBook", "indices": [109, 118]}, {"text": "NanoCore", "indices": [132, 141]}, {"text": "Remcos", "indices": [155, 162]}, {"text": "Ursnif", "indices": [174, 181]}, {"text": "HawkEye", "indices": [193, 201]}, {"text": "AZORult", "indices": [214, 222]}, {"text": "Pyrogenic", "indices": [234, 244]}], "symbols": [], "user_mentions": [], "urls": [{"url": "https://t.co/98nRpXOxWw", "expanded_url": "https://any.run/malware-trends/", "display_url": "any.run/malware-trends/", "indices": [253, 276]}]}, "metadata": {"iso_language_code": "en", "result_type": "recent"}, "source": "<a href=\"https://mobile.twitter.com\" rel=\"nofollow\">Twitter Web App</a>", "in_reply_to_status_id": null, "in_reply_to_status_id_str": null, "in_reply_to_user_id": null, "in_reply_to_user_id_str": null, "in_reply_to_screen_name": null, "user": {"id": 833639043862786048, "id_str": "833639043862786048", "name": "ANY.RUN", "screen_name": "anyrun_app", "location": "", "description": "Interactive #malware analysis service. Useful for dynamic research of most types of #cyberthreats using any environments.", "url": "https://t.co/ksXUw2hK1m", "entities": {"url": {"urls": [{"url": "https://t.co/ksXUw2hK1m", "expanded_url": "https://www.any.run/", "display_url": "any.run", "indices": [0, 23]}]}, "description": {"urls": []}}, "protected": false, "followers_count": 10499, "friends_count": 175, "listed_count": 188, "created_at": "Mon Feb 20 11:26:51 +0000 2017", "favourites_count": 2359, "utc_offset": null, "time_zone": null, "geo_enabled": false, "verified": false, "statuses_count": 1131, "lang": null, "contributors_enabled": false, "is_translator": false, "is_translation_enabled": false, "profile_background_color": "000000", "profile_background_image_url": "http://abs.twimg.com/images/themes/theme1/bg.png", "profile_background_image_url_https": "https://abs.twimg.com/images/themes/theme1/bg.png", "profile_background_tile": false, "profile_image_url": "http://pbs.twimg.com/profile_images/888000026437447681/upTlRuwp_normal.jpg", "profile_image_url_https": "https://pbs.twimg.com/profile_images/888000026437447681/upTlRuwp_normal.jpg", "profile_banner_url": "https://pbs.twimg.com/profile_banners/833639043862786048/1518700753", "profile_link_color": "377C9D", "profile_sidebar_border_color": "000000", "profile_sidebar_fill_color": "000000", "profile_text_color": "000000", "profile_use_background_image": false, "has_extended_profile": false, "default_profile": false, "default_profile_image": false, "following": false, "follow_request_sent": false, "notifications": false, "translator_type": "none"}, "geo": null, "coordinates": null, "place": null, "contributors": null, "is_quote_status": false, "retweet_count": 7, "favorite_count": 12, "favorited": false, "retweeted": false, "possibly_sensitive": false, "lang": "en"}, "is_quote_status": false, "retweet_count": 7, "favorite_count": 0, "favorited": false, "retweeted": false, "possibly_sensitive": false, "lang": "en"}, {"created_at": "Mon Feb 24 08:02:36 +0000 2020", "id": 1231851910287810562, "id_str": "1231851910287810562", "full_text": "RT @anyrun_app: TOP10 last week's threats by uploads\n\n⬇️ #Emotet 255 (270)\n⬆️ #LokiBot 235 (211)\n⬇️ #AgentTesla 167 (325)\n⬇️ #FormBook 125…", "truncated": false, "display_text_range": [0, 139], "entities": {"hashtags": [{"text": "Emotet", "indices": [57, 64]}, {"text": "LokiBot", "indices": [78, 86]}, {"text": "AgentTesla", "indices": [100, 111]}, {"text": "FormBook", "indices": [125, 134]}], "symbols": [], "user_mentions": [{"screen_name": "anyrun_app", "name": "ANY.RUN", "id": 833639043862786048, "id_str": "833639043862786048", "indices": [3, 14]}], "urls": []}, "metadata": {"iso_language_code": "en", "result_type": "recent"}, "source": "<a href=\"http://twitter.com/download/android\" rel=\"nofollow\">Twitter for Android</a>", "in_reply_to_status_id": null, "in_reply_to_status_id_str": null, "in_reply_to_user_id": null, "in_reply_to_user_id_str": null, "in_reply_to_screen_name": null, "user": {"id": 700868921298124801, "id_str": "700868921298124801", "name": "DROL Security", "screen_name": "DrolSecurity", "location": "", "description": "Not my Day Job", "url": null, "entities": {"description": {"urls": []}}, "protected": false, "followers_count": 491, "friends_count": 789, "listed_count": 102, "created_at": "Sat Feb 20 02:25:47 +0000 2016", "favourites_count": 33012, "utc_offset": null, "time_zone": null, "geo_enabled": false, "verified": false, "statuses_count": 20723, "lang": null, "contributors_enabled": false, "is_translator": false, "is_translation_enabled": false, "profile_background_color": "F5F8FA", "profile_background_image_url": null, "profile_background_image_url_https": null, "profile_background_tile": false, "profile_image_url": "http://pbs.twimg.com/profile_images/771880593160364032/OpJbFLL4_normal.jpg", "profile_image_url_https": "https://pbs.twimg.com/profile_images/771880593160364032/OpJbFLL4_normal.jpg", "profile_banner_url": "https://pbs.twimg.com/profile_banners/700868921298124801/1458358683", "profile_link_color": "1DA1F2", "profile_sidebar_border_color": "C0DEED", "profile_sidebar_fill_color": "DDEEF6", "profile_text_color": "333333", "profile_use_background_image": true, "has_extended_profile": false, "default_profile": true, "default_profile_image": false, "following": false, "follow_request_sent": false, "notifications": false, "translator_type": "none"}, "geo": null, "coordinates": null, "place": null, "contributors": null, "retweeted_status": {"created_at": "Mon Feb 24 06:04:45 +0000 2020", "id": 1231822251382788096, "id_str": "1231822251382788096", "full_text": "TOP10 last week's threats by uploads\n\n⬇️ #Emotet 255 (270)\n⬆️ #LokiBot 235 (211)\n⬇️ #AgentTesla 167 (325)\n⬇️ #FormBook 125 (141)\n⬇️ #NanoCore 116 (168)\n⬆️ #Remcos 82 (66)\n⬇️ #Ursnif 81 (94)\n⬇️ #HawkEye 73 (148)\n⬇️ #AZORult 57 (95)\n⬆️ #Pyrogenic 53 (5)\n\nhttps://t.co/98nRpXOxWw", "truncated": false, "display_text_range": [0, 276], "entities": {"hashtags": [{"text": "Emotet", "indices": [41, 48]}, {"text": "LokiBot", "indices": [62, 70]}, {"text": "AgentTesla", "indices": [84, 95]}, {"text": "FormBook", "indices": [109, 118]}, {"text": "NanoCore", "indices": [132, 141]}, {"text": "Remcos", "indices": [155, 162]}, {"text": "Ursnif", "indices": [174, 181]}, {"text": "HawkEye", "indices": [193, 201]}, {"text": "AZORult", "indices": [214, 222]}, {"text": "Pyrogenic", "indices": [234, 244]}], "symbols": [], "user_mentions": [], "urls": [{"url": "https://t.co/98nRpXOxWw", "expanded_url": "https://any.run/malware-trends/", "display_url": "any.run/malware-trends/", "indices": [253, 276]}]}, "metadata": {"iso_language_code": "en", "result_type": "recent"}, "source": "<a href=\"https://mobile.twitter.com\" rel=\"nofollow\">Twitter Web App</a>", "in_reply_to_status_id": null, "in_reply_to_status_id_str": null, "in_reply_to_user_id": null, "in_reply_to_user_id_str": null, "in_reply_to_screen_name": null, "user": {"id": 833639043862786048, "id_str": "833639043862786048", "name": "ANY.RUN", "screen_name": "anyrun_app", "location": "", "description": "Interactive #malware analysis service. Useful for dynamic research of most types of #cyberthreats using any environments.", "url": "https://t.co/ksXUw2hK1m", "entities": {"url": {"urls": [{"url": "https://t.co/ksXUw2hK1m", "expanded_url": "https://www.any.run/", "display_url": "any.run", "indices": [0, 23]}]}, "description": {"urls": []}}, "protected": false, "followers_count": 10499, "friends_count": 175, "listed_count": 188, "created_at": "Mon Feb 20 11:26:51 +0000 2017", "favourites_count": 2359, "utc_offset": null, "time_zone": null, "geo_enabled": false, "verified": false, "statuses_count": 1131, "lang": null, "contributors_enabled": false, "is_translator": false, "is_translation_enabled": false, "profile_background_color": "000000", "profile_background_image_url": "http://abs.twimg.com/images/themes/theme1/bg.png", "profile_background_image_url_https": "https://abs.twimg.com/images/themes/theme1/bg.png", "profile_background_tile": false, "profile_image_url": "http://pbs.twimg.com/profile_images/888000026437447681/upTlRuwp_normal.jpg", "profile_image_url_https": "https://pbs.twimg.com/profile_images/888000026437447681/upTlRuwp_normal.jpg", "profile_banner_url": "https://pbs.twimg.com/profile_banners/833639043862786048/1518700753", "profile_link_color": "377C9D", "profile_sidebar_border_color": "000000", "profile_sidebar_fill_color": "000000", "profile_text_color": "000000", "profile_use_background_image": false, "has_extended_profile": false, "default_profile": false, "default_profile_image": false, "following": false, "follow_request_sent": false, "notifications": false, "translator_type": "none"}, "geo": null, "coordinates": null, "place": null, "contributors": null, "is_quote_status": false, "retweet_count": 7, "favorite_count": 12, "favorited": false, "retweeted": false, "possibly_sensitive": false, "lang": "en"}, "is_quote_status": false, "retweet_count": 7, "favorite_count": 0, "favorited": false, "retweeted": false, "possibly_sensitive": false, "lang": "en"}, {"created_at": "Mon Feb 24 06:58:48 +0000 2020", "id": 1231835853380517891, "id_str": "1231835853380517891", "full_text": "RT @anyrun_app: TOP10 last week's threats by uploads\n\n⬇️ #Emotet 255 (270)\n⬆️ #LokiBot 235 (211)\n⬇️ #AgentTesla 167 (325)\n⬇️ #FormBook 125…", "truncated": false, "display_text_range": [0, 139], "entities": {"hashtags": [{"text": "Emotet", "indices": [57, 64]}, {"text": "LokiBot", "indices": [78, 86]}, {"text": "AgentTesla", "indices": [100, 111]}, {"text": "FormBook", "indices": [125, 134]}], "symbols": [], "user_mentions": [{"screen_name": "anyrun_app", "name": "ANY.RUN", "id": 833639043862786048, "id_str": "833639043862786048", "indices": [3, 14]}], "urls": []}, "metadata": {"iso_language_code": "en", "result_type": "recent"}, "source": "<a href=\"http://twitter.com/download/android\" rel=\"nofollow\">Twitter for Android</a>", "in_reply_to_status_id": null, "in_reply_to_status_id_str": null, "in_reply_to_user_id": null, "in_reply_to_user_id_str": null, "in_reply_to_screen_name": null, "user": {"id": 982533264, "id_str": "982533264", "name": "Herbie Zimmerman", "screen_name": "HerbieZimmerman", "location": "", "description": "SOC analyst/wanna-be malware researcher.", "url": "https://t.co/OIptwjW0Mj", "entities": {"url": {"urls": [{"url": "https://t.co/OIptwjW0Mj", "expanded_url": "https://www.herbiez.com", "display_url": "herbiez.com", "indices": [0, 23]}]}, "description": {"urls": []}}, "protected": false, "followers_count": 1454, "friends_count": 674, "listed_count": 40, "created_at": "Sat Dec 01 13:26:30 +0000 2012", "favourites_count": 5845, "utc_offset": null, "time_zone": null, "geo_enabled": false, "verified": false, "statuses_count": 2493, "lang": null, "contributors_enabled": false, "is_translator": false, "is_translation_enabled": false, "profile_background_color": "C0DEED", "profile_background_image_url": "http://abs.twimg.com/images/themes/theme1/bg.png", "profile_background_image_url_https": "https://abs.twimg.com/images/themes/theme1/bg.png", "profile_background_tile": false, "profile_image_url": "http://pbs.twimg.com/profile_images/3447079452/b50595501b5cc6820a90ea66c0df94f4_normal.jpeg", "profile_image_url_https": "https://pbs.twimg.com/profile_images/3447079452/b50595501b5cc6820a90ea66c0df94f4_normal.jpeg", "profile_link_color": "1DA1F2", "profile_sidebar_border_color": "C0DEED", "profile_sidebar_fill_color": "DDEEF6", "profile_text_color": "333333", "profile_use_background_image": true, "has_extended_profile": false, "default_profile": true, "default_profile_image": false, "following": false, "follow_request_sent": false, "notifications": false, "translator_type": "none"}, "geo": null, "coordinates": null, "place": null, "contributors": null, "retweeted_status": {"created_at": "Mon Feb 24 06:04:45 +0000 2020", "id": 1231822251382788096, "id_str": "1231822251382788096", "full_text": "TOP10 last week's threats by uploads\n\n⬇️ #Emotet 255 (270)\n⬆️ #LokiBot 235 (211)\n⬇️ #AgentTesla 167 (325)\n⬇️ #FormBook 125 (141)\n⬇️ #NanoCore 116 (168)\n⬆️ #Remcos 82 (66)\n⬇️ #Ursnif 81 (94)\n⬇️ #HawkEye 73 (148)\n⬇️ #AZORult 57 (95)\n⬆️ #Pyrogenic 53 (5)\n\nhttps://t.co/98nRpXOxWw", "truncated": false, "display_text_range": [0, 276], "entities": {"hashtags": [{"text": "Emotet", "indices": [41, 48]}, {"text": "LokiBot", "indices": [62, 70]}, {"text": "AgentTesla", "indices": [84, 95]}, {"text": "FormBook", "indices": [109, 118]}, {"text": "NanoCore", "indices": [132, 141]}, {"text": "Remcos", "indices": [155, 162]}, {"text": "Ursnif", "indices": [174, 181]}, {"text": "HawkEye", "indices": [193, 201]}, {"text": "AZORult", "indices": [214, 222]}, {"text": "Pyrogenic", "indices": [234, 244]}], "symbols": [], "user_mentions": [], "urls": [{"url": "https://t.co/98nRpXOxWw", "expanded_url": "https://any.run/malware-trends/", "display_url": "any.run/malware-trends/", "indices": [253, 276]}]}, "metadata": {"iso_language_code": "en", "result_type": "recent"}, "source": "<a href=\"https://mobile.twitter.com\" rel=\"nofollow\">Twitter Web App</a>", "in_reply_to_status_id": null, "in_reply_to_status_id_str": null, "in_reply_to_user_id": null, "in_reply_to_user_id_str": null, "in_reply_to_screen_name": null, "user": {"id": 833639043862786048, "id_str": "833639043862786048", "name": "ANY.RUN", "screen_name": "anyrun_app", "location": "", "description": "Interactive #malware analysis service. Useful for dynamic research of most types of #cyberthreats using any environments.", "url": "https://t.co/ksXUw2hK1m", "entities": {"url": {"urls": [{"url": "https://t.co/ksXUw2hK1m", "expanded_url": "https://www.any.run/", "display_url": "any.run", "indices": [0, 23]}]}, "description": {"urls": []}}, "protected": false, "followers_count": 10499, "friends_count": 175, "listed_count": 188, "created_at": "Mon Feb 20 11:26:51 +0000 2017", "favourites_count": 2359, "utc_offset": null, "time_zone": null, "geo_enabled": false, "verified": false, "statuses_count": 1131, "lang": null, "contributors_enabled": false, "is_translator": false, "is_translation_enabled": false, "profile_background_color": "000000", "profile_background_image_url": "http://abs.twimg.com/images/themes/theme1/bg.png", "profile_background_image_url_https": "https://abs.twimg.com/images/themes/theme1/bg.png", "profile_background_tile": false, "profile_image_url": "http://pbs.twimg.com/profile_images/888000026437447681/upTlRuwp_normal.jpg", "profile_image_url_https": "https://pbs.twimg.com/profile_images/888000026437447681/upTlRuwp_normal.jpg", "profile_banner_url": "https://pbs.twimg.com/profile_banners/833639043862786048/1518700753", "profile_link_color": "377C9D", "profile_sidebar_border_color": "000000", "profile_sidebar_fill_color": "000000", "profile_text_color": "000000", "profile_use_background_image": false, "has_extended_profile": false, "default_profile": false, "default_profile_image": false, "following": false, "follow_request_sent": false, "notifications": false, "translator_type": "none"}, "geo": null, "coordinates": null, "place": null, "contributors": null, "is_quote_status": false, "retweet_count": 7, "favorite_count": 12, "favorited": false, "retweeted": false, "possibly_sensitive": false, "lang": "en"}, "is_quote_status": false, "retweet_count": 7, "favorite_count": 0, "favorited": false, "retweeted": false, "possibly_sensitive": false, "lang": "en"}, {"created_at": "Mon Feb 24 06:04:45 +0000 2020", "id": 1231822251382788096, "id_str": "1231822251382788096", "full_text": "TOP10 last week's threats by uploads\n\n⬇️ #Emotet 255 (270)\n⬆️ #LokiBot 235 (211)\n⬇️ #AgentTesla 167 (325)\n⬇️ #FormBook 125 (141)\n⬇️ #NanoCore 116 (168)\n⬆️ #Remcos 82 (66)\n⬇️ #Ursnif 81 (94)\n⬇️ #HawkEye 73 (148)\n⬇️ #AZORult 57 (95)\n⬆️ #Pyrogenic 53 (5)\n\nhttps://t.co/98nRpXOxWw", "truncated": false, "display_text_range": [0, 276], "entities": {"hashtags": [{"text": "Emotet", "indices": [41, 48]}, {"text": "LokiBot", "indices": [62, 70]}, {"text": "AgentTesla", "indices": [84, 95]}, {"text": "FormBook", "indices": [109, 118]}, {"text": "NanoCore", "indices": [132, 141]}, {"text": "Remcos", "indices": [155, 162]}, {"text": "Ursnif", "indices": [174, 181]}, {"text": "HawkEye", "indices": [193, 201]}, {"text": "AZORult", "indices": [214, 222]}, {"text": "Pyrogenic", "indices": [234, 244]}], "symbols": [], "user_mentions": [], "urls": [{"url": "https://t.co/98nRpXOxWw", "expanded_url": "https://any.run/malware-trends/", "display_url": "any.run/malware-trends/", "indices": [253, 276]}]}, "metadata": {"iso_language_code": "en", "result_type": "recent"}, "source": "<a href=\"https://mobile.twitter.com\" rel=\"nofollow\">Twitter Web App</a>", "in_reply_to_status_id": null, "in_reply_to_status_id_str": null, "in_reply_to_user_id": null, "in_reply_to_user_id_str": null, "in_reply_to_screen_name": null, "user": {"id": 833639043862786048, "id_str": "833639043862786048", "name": "ANY.RUN", "screen_name": "anyrun_app", "location": "", "description": "Interactive #malware analysis service. Useful for dynamic research of most types of #cyberthreats using any environments.", "url": "https://t.co/ksXUw2hK1m", "entities": {"url": {"urls": [{"url": "https://t.co/ksXUw2hK1m", "expanded_url": "https://www.any.run/", "display_url": "any.run", "indices": [0, 23]}]}, "description": {"urls": []}}, "protected": false, "followers_count": 10499, "friends_count": 175, "listed_count": 188, "created_at": "Mon Feb 20 11:26:51 +0000 2017", "favourites_count": 2359, "utc_offset": null, "time_zone": null, "geo_enabled": false, "verified": false, "statuses_count": 1131, "lang": null, "contributors_enabled": false, "is_translator": false, "is_translation_enabled": false, "profile_background_color": "000000", "profile_background_image_url": "http://abs.twimg.com/images/themes/theme1/bg.png", "profile_background_image_url_https": "https://abs.twimg.com/images/themes/theme1/bg.png", "profile_background_tile": false, "profile_image_url": "http://pbs.twimg.com/profile_images/888000026437447681/upTlRuwp_normal.jpg", "profile_image_url_https": "https://pbs.twimg.com/profile_images/888000026437447681/upTlRuwp_normal.jpg", "profile_banner_url": "https://pbs.twimg.com/profile_banners/833639043862786048/1518700753", "profile_link_color": "377C9D", "profile_sidebar_border_color": "000000", "profile_sidebar_fill_color": "000000", "profile_text_color": "000000", "profile_use_background_image": false, "has_extended_profile": false, "default_profile": false, "default_profile_image": false, "following": false, "follow_request_sent": false, "notifications": false, "translator_type": "none"}, "geo": null, "coordinates": null, "place": null, "contributors": null, "is_quote_status": false, "retweet_count": 7, "favorite_count": 12, "favorited": false, "retweeted": false, "possibly_sensitive": false, "lang": "en"}, {"created_at": "Fri Feb 21 04:33:33 +0000 2020", "id": 1230712135811883009, "id_str": "1230712135811883009", "full_text": "RT @argevise: TOP10 last week's threats by uploads\n\n⬇️ #AgentTesla 325 (410)\n⬇️ #Emotet 275 (1259)\n⬇️ #LokiBot 211 (253)\n⬆️ #NanoCore 168 (…", "truncated": false, "display_text_range": [0, 140], "entities": {"hashtags": [{"text": "AgentTesla", "indices": [55, 66]}, {"text": "Emotet", "indices": [80, 87]}, {"text": "LokiBot", "indices": [102, 110]}, {"text": "NanoCore", "indices": [124, 133]}], "symbols": [], "user_mentions": [{"screen_name": "argevise", "name": "Martial Gervaise", "id": 56174262, "id_str": "56174262", "indices": [3, 12]}], "urls": []}, "metadata": {"iso_language_code": "en", "result_type": "recent"}, "source": "<a href=\"http://twitter.com/download/android\" rel=\"nofollow\">Twitter for Android</a>", "in_reply_to_status_id": null, "in_reply_to_status_id_str": null, "in_reply_to_user_id": null, "in_reply_to_user_id_str": null, "in_reply_to_screen_name": null, "user": {"id": 3108337398, "id_str": "3108337398", "name": "The InfoSec Slow Worm!", "screen_name": "SlowWormSec", "location": "Texas, USA", "description": "InfoSec | Coffee | Skyrim | MBTI: ENTP | #twitterweekendshift | RT's = Endorsements", "url": "https://t.co/c6KEDCp7sv", "entities": {"url": {"urls": [{"url": "https://t.co/c6KEDCp7sv", "expanded_url": "https://mendanddefend.com", "display_url": "mendanddefend.com", "indices": [0, 23]}]}, "description": {"urls": []}}, "protected": false, "followers_count": 1015, "friends_count": 1160, "listed_count": 15, "created_at": "Thu Mar 26 15:53:28 +0000 2015", "favourites_count": 26765, "utc_offset": null, "time_zone": null, "geo_enabled": false, "verified": false, "statuses_count": 467, "lang": null, "contributors_enabled": false, "is_translator": false, "is_translation_enabled": false, "profile_background_color": "000000", "profile_background_image_url": "http://abs.twimg.com/images/themes/theme1/bg.png", "profile_background_image_url_https": "https://abs.twimg.com/images/themes/theme1/bg.png", "profile_background_tile": false, "profile_image_url": "http://pbs.twimg.com/profile_images/1216073653579911169/Ywggob6k_normal.jpg", "profile_image_url_https": "https://pbs.twimg.com/profile_images/1216073653579911169/Ywggob6k_normal.jpg", "profile_banner_url": "https://pbs.twimg.com/profile_banners/3108337398/1582068280", "profile_link_color": "19CF86", "profile_sidebar_border_color": "000000", "profile_sidebar_fill_color": "000000", "profile_text_color": "000000", "profile_use_background_image": false, "has_extended_profile": false, "default_profile": false, "default_profile_image": false, "following": false, "follow_request_sent": false, "notifications": false, "translator_type": "none"}, "geo": null, "coordinates": null, "place": null, "contributors": null, "retweeted_status": {"created_at": "Wed Feb 19 10:31:19 +0000 2020", "id": 1230077395929063424, "id_str": "1230077395929063424", "full_text": "TOP10 last week's threats by uploads\n\n⬇️ #AgentTesla 325 (410)\n⬇️ #Emotet 275 (1259)\n⬇️ #LokiBot 211 (253)\n⬆️ #NanoCore 168 (104)\n⬆️ #HawkEye 148 (89)\n⬇️ #FormBook 141 (151)\n⬇️ #NjRAT 100 (109)\n⬆️ #AZORult 95 (55)\n⬆️ #Ursnif 94 (82)\n⬇️ #Remcos 66 (70)\nhttps://t.co/2HvUUeewoD", "truncated": false, "display_text_range": [0, 275], "entities": {"hashtags": [{"text": "AgentTesla", "indices": [41, 52]}, {"text": "Emotet", "indices": [66, 73]}, {"text": "LokiBot", "indices": [88, 96]}, {"text": "NanoCore", "indices": [110, 119]}, {"text": "HawkEye", "indices": [133, 141]}, {"text": "FormBook", "indices": [154, 163]}, {"text": "NjRAT", "indices": [177, 183]}, {"text": "AZORult", "indices": [197, 205]}, {"text": "Ursnif", "indices": [217, 224]}, {"text": "Remcos", "indices": [236, 243]}], "symbols": [], "user_mentions": [], "urls": [{"url": "https://t.co/2HvUUeewoD", "expanded_url": "https://any.run/malware-trends/", "display_url": "any.run/malware-trends/", "indices": [252, 275]}]}, "metadata": {"iso_language_code": "en", "result_type": "recent"}, "source": "<a href=\"http://twitter.com/download/iphone\" rel=\"nofollow\">Twitter for iPhone</a>", "in_reply_to_status_id": null, "in_reply_to_status_id_str": null, "in_reply_to_user_id": null, "in_reply_to_user_id_str": null, "in_reply_to_screen_name": null, "user": {"id": 56174262, "id_str": "56174262", "name": "Martial Gervaise", "screen_name": "argevise", "location": "Paris, Rouen, Rennes, Dallas", "description": "Deputy of Cyber-Security Director. Passionate by digital technologies and their usages. (my own tweets do not represent my company)", "url": "https://t.co/nvyfFOnVi4", "entities": {"url": {"urls": [{"url": "https://t.co/nvyfFOnVi4", "expanded_url": "https://www.ip-paris.fr/", "display_url": "ip-paris.fr", "indices": [0, 23]}]}, "description": {"urls": []}}, "protected": false, "followers_count": 3572, "friends_count": 5001, "listed_count": 221, "created_at": "Sun Jul 12 19:50:43 +0000 2009", "favourites_count": 17868, "utc_offset": null, "time_zone": null, "geo_enabled": true, "verified": false, "statuses_count": 25617, "lang": null, "contributors_enabled": false, "is_translator": false, "is_translation_enabled": false, "profile_background_color": "C6E2EE", "profile_background_image_url": "http://abs.twimg.com/images/themes/theme1/bg.png", "profile_background_image_url_https": "https://abs.twimg.com/images/themes/theme1/bg.png", "profile_background_tile": false, "profile_image_url": "http://pbs.twimg.com/profile_images/427109767572905984/1DOKiOIM_normal.jpeg", "profile_image_url_https": "https://pbs.twimg.com/profile_images/427109767572905984/1DOKiOIM_normal.jpeg", "profile_banner_url": "https://pbs.twimg.com/profile_banners/56174262/1391271218", "profile_link_color": "1F98C7", "profile_sidebar_border_color": "C6E2EE", "profile_sidebar_fill_color": "DAECF4", "profile_text_color": "663B12", "profile_use_background_image": true, "has_extended_profile": false, "default_profile": false, "default_profile_image": false, "following": false, "follow_request_sent": false, "notifications": false, "translator_type": "none"}, "geo": null, "coordinates": null, "place": null, "contributors": null, "is_quote_status": false, "retweet_count": 3, "favorite_count": 5, "favorited": false, "retweeted": false, "possibly_sensitive": false, "lang": "en"}, "is_quote_status": false, "retweet_count": 3, "favorite_count": 0, "favorited": false, "retweeted": false, "possibly_sensitive": false, "lang": "en"}, {"created_at": "Thu Feb 20 18:19:05 +0000 2020", "id": 1230557502862843904, "id_str": "1230557502862843904", "full_text": "@wwp96 @JAMESWT_MHT That was marked as #nanocore in https[:]//ghostbin.com/paste/qyhf6 (currently offline). Will move to #remcos to be OK with port number.", "truncated": false, "display_text_range": [20, 155], "entities": {"hashtags": [{"text": "nanocore", "indices": [39, 48]}, {"text": "remcos", "indices": [121, 128]}], "symbols": [], "user_mentions": [{"screen_name": "wwp96", "name": "wwp96", "id": 844560243250081792, "id_str": "844560243250081792", "indices": [0, 6]}, {"screen_name": "JAMESWT_MHT", "name": "JAMESWT", "id": 3433210978, "id_str": "3433210978", "indices": [7, 19]}], "urls": []}, "metadata": {"iso_language_code": "en", "result_type": "recent"}, "source": "<a href=\"https://mobile.twitter.com\" rel=\"nofollow\">Twitter Web App</a>", "in_reply_to_status_id": 1230524414355296259, "in_reply_to_status_id_str": "1230524414355296259", "in_reply_to_user_id": 844560243250081792, "in_reply_to_user_id_str": "844560243250081792", "in_reply_to_screen_name": "wwp96", "user": {"id": 4820426207, "id_str": "4820426207", "name": "Mikhail Kasimov", "screen_name": "500mk500", "location": "Ukraine, Kiev", "description": "Linux user, Information Security, IT, technical writer, editor", "url": null, "entities": {"description": {"urls": []}}, "protected": false, "followers_count": 62, "friends_count": 236, "listed_count": 3, "created_at": "Sun Jan 17 07:45:52 +0000 2016", "favourites_count": 1601, "utc_offset": null, "time_zone": null, "geo_enabled": false, "verified": false, "statuses_count": 525, "lang": null, "contributors_enabled": false, "is_translator": false, "is_translation_enabled": false, "profile_background_color": "C6E2EE", "profile_background_image_url": "http://abs.twimg.com/images/themes/theme2/bg.gif", "profile_background_image_url_https": "https://abs.twimg.com/images/themes/theme2/bg.gif", "profile_background_tile": false, "profile_image_url": "http://pbs.twimg.com/profile_images/688628691660853248/gOAFG8hf_normal.png", "profile_image_url_https": "https://pbs.twimg.com/profile_images/688628691660853248/gOAFG8hf_normal.png", "profile_banner_url": "https://pbs.twimg.com/profile_banners/4820426207/1454344805", "profile_link_color": "4A913C", "profile_sidebar_border_color": "000000", "profile_sidebar_fill_color": "000000", "profile_text_color": "000000", "profile_use_background_image": true, "has_extended_profile": false, "default_profile": false, "default_profile_image": false, "following": false, "follow_request_sent": false, "notifications": false, "translator_type": "none"}, "geo": null, "coordinates": null, "place": null, "contributors": null, "is_quote_status": false, "retweet_count": 0, "favorite_count": 1, "favorited": false, "retweeted": false, "lang": "en"}, {"created_at": "Thu Feb 20 16:52:48 +0000 2020", "id": 1230535785771917312, "id_str": "1230535785771917312", "full_text": "#nanocore @JAMESWT_MHT \n\n/chommyflozy.duckdns.org\n\n7fedd833e4c415295939fc8844d8dae8\n7f31dc3a5051c517193b3655d2ef96db\n\nhttps://t.co/peLRwL9J0g", "truncated": false, "display_text_range": [0, 141], "entities": {"hashtags": [{"text": "nanocore", "indices": [0, 9]}], "symbols": [], "user_mentions": [{"screen_name": "JAMESWT_MHT", "name": "JAMESWT", "id": 3433210978, "id_str": "3433210978", "indices": [10, 22]}], "urls": [{"url": "https://t.co/peLRwL9J0g", "expanded_url": "https://app.any.run/tasks/b189ea2d-e898-4ad6-97ce-66fe74244783", "display_url": "app.any.run/tasks/b189ea2d…", "indices": [118, 141]}]}, "metadata": {"iso_language_code": "en", "result_type": "recent"}, "source": "<a href=\"https://about.twitter.com/products/tweetdeck\" rel=\"nofollow\">TweetDeck</a>", "in_reply_to_status_id": null, "in_reply_to_status_id_str": null, "in_reply_to_user_id": null, "in_reply_to_user_id_str": null, "in_reply_to_screen_name": null, "user": {"id": 844560243250081792, "id_str": "844560243250081792", "name": "wwp96", "screen_name": "wwp96", "location": "", "description": "Good huntin'", "url": null, "entities": {"description": {"urls": []}}, "protected": false, "followers_count": 353, "friends_count": 885, "listed_count": 12, "created_at": "Wed Mar 22 14:43:47 +0000 2017", "favourites_count": 797, "utc_offset": null, "time_zone": null, "geo_enabled": false, "verified": false, "statuses_count": 1175, "lang": null, "contributors_enabled": false, "is_translator": false, "is_translation_enabled": false, "profile_background_color": "000000", "profile_background_image_url": "http://abs.twimg.com/images/themes/theme1/bg.png", "profile_background_image_url_https": "https://abs.twimg.com/images/themes/theme1/bg.png", "profile_background_tile": false, "profile_image_url": "http://pbs.twimg.com/profile_images/1160968289125904385/Lc3x9slQ_normal.jpg", "profile_image_url_https": "https://pbs.twimg.com/profile_images/1160968289125904385/Lc3x9slQ_normal.jpg", "profile_link_color": "000000", "profile_sidebar_border_color": "000000", "profile_sidebar_fill_color": "000000", "profile_text_color": "000000", "profile_use_background_image": false, "has_extended_profile": false, "default_profile": false, "default_profile_image": false, "following": false, "follow_request_sent": false, "notifications": false, "translator_type": "none"}, "geo": null, "coordinates": null, "place": null, "contributors": null, "is_quote_status": false, "retweet_count": 0, "favorite_count": 1, "favorited": false, "retweeted": false, "possibly_sensitive": false, "lang": "en"}, {"created_at": "Thu Feb 20 16:08:58 +0000 2020", "id": 1230524755830329346, "id_str": "1230524755830329346", "full_text": "@wwp96 @JAMESWT_MHT I also have a #remcos variation for 1005. Will re-check for #nanocore -- if it is true, or should I fix category on my side.", "truncated": false, "display_text_range": [20, 144], "entities": {"hashtags": [{"text": "remcos", "indices": [34, 41]}, {"text": "nanocore", "indices": [80, 89]}], "symbols": [], "user_mentions": [{"screen_name": "wwp96", "name": "wwp96", "id": 844560243250081792, "id_str": "844560243250081792", "indices": [0, 6]}, {"screen_name": "JAMESWT_MHT", "name": "JAMESWT", "id": 3433210978, "id_str": "3433210978", "indices": [7, 19]}], "urls": []}, "metadata": {"iso_language_code": "en", "result_type": "recent"}, "source": "<a href=\"https://mobile.twitter.com\" rel=\"nofollow\">Twitter Web App</a>", "in_reply_to_status_id": 1230524414355296259, "in_reply_to_status_id_str": "1230524414355296259", "in_reply_to_user_id": 844560243250081792, "in_reply_to_user_id_str": "844560243250081792", "in_reply_to_screen_name": "wwp96", "user": {"id": 4820426207, "id_str": "4820426207", "name": "Mikhail Kasimov", "screen_name": "500mk500", "location": "Ukraine, Kiev", "description": "Linux user, Information Security, IT, technical writer, editor", "url": null, "entities": {"description": {"urls": []}}, "protected": false, "followers_count": 62, "friends_count": 236, "listed_count": 3, "created_at": "Sun Jan 17 07:45:52 +0000 2016", "favourites_count": 1601, "utc_offset": null, "time_zone": null, "geo_enabled": false, "verified": false, "statuses_count": 525, "lang": null, "contributors_enabled": false, "is_translator": false, "is_translation_enabled": false, "profile_background_color": "C6E2EE", "profile_background_image_url": "http://abs.twimg.com/images/themes/theme2/bg.gif", "profile_background_image_url_https": "https://abs.twimg.com/images/themes/theme2/bg.gif", "profile_background_tile": false, "profile_image_url": "http://pbs.twimg.com/profile_images/688628691660853248/gOAFG8hf_normal.png", "profile_image_url_https": "https://pbs.twimg.com/profile_images/688628691660853248/gOAFG8hf_normal.png", "profile_banner_url": "https://pbs.twimg.com/profile_banners/4820426207/1454344805", "profile_link_color": "4A913C", "profile_sidebar_border_color": "000000", "profile_sidebar_fill_color": "000000", "profile_text_color": "000000", "profile_use_background_image": true, "has_extended_profile": false, "default_profile": false, "default_profile_image": false, "following": false, "follow_request_sent": false, "notifications": false, "translator_type": "none"}, "geo": null, "coordinates": null, "place": null, "contributors": null, "is_quote_status": false, "retweet_count": 0, "favorite_count": 0, "favorited": false, "retweeted": false, "lang": "en"}, {"created_at": "Thu Feb 20 16:03:19 +0000 2020", "id": 1230523335714525189, "id_str": "1230523335714525189", "full_text": "@wwp96 @JAMESWT_MHT :1005 is in use of #nanocore", "truncated": false, "display_text_range": [20, 48], "entities": {"hashtags": [{"text": "nanocore", "indices": [39, 48]}], "symbols": [], "user_mentions": [{"screen_name": "wwp96", "name": "wwp96", "id": 844560243250081792, "id_str": "844560243250081792", "indices": [0, 6]}, {"screen_name": "JAMESWT_MHT", "name": "JAMESWT", "id": 3433210978, "id_str": "3433210978", "indices": [7, 19]}], "urls": []}, "metadata": {"iso_language_code": "en", "result_type": "recent"}, "source": "<a href=\"https://mobile.twitter.com\" rel=\"nofollow\">Twitter Web App</a>", "in_reply_to_status_id": 1230522765133983744, "in_reply_to_status_id_str": "1230522765133983744", "in_reply_to_user_id": 844560243250081792, "in_reply_to_user_id_str": "844560243250081792", "in_reply_to_screen_name": "wwp96", "user": {"id": 4820426207, "id_str": "4820426207", "name": "Mikhail Kasimov", "screen_name": "500mk500", "location": "Ukraine, Kiev", "description": "Linux user, Information Security, IT, technical writer, editor", "url": null, "entities": {"description": {"urls": []}}, "protected": false, "followers_count": 62, "friends_count": 236, "listed_count": 3, "created_at": "Sun Jan 17 07:45:52 +0000 2016", "favourites_count": 1601, "utc_offset": null, "time_zone": null, "geo_enabled": false, "verified": false, "statuses_count": 525, "lang": null, "contributors_enabled": false, "is_translator": false, "is_translation_enabled": false, "profile_background_color": "C6E2EE", "profile_background_image_url": "http://abs.twimg.com/images/themes/theme2/bg.gif", "profile_background_image_url_https": "https://abs.twimg.com/images/themes/theme2/bg.gif", "profile_background_tile": false, "profile_image_url": "http://pbs.twimg.com/profile_images/688628691660853248/gOAFG8hf_normal.png", "profile_image_url_https": "https://pbs.twimg.com/profile_images/688628691660853248/gOAFG8hf_normal.png", "profile_banner_url": "https://pbs.twimg.com/profile_banners/4820426207/1454344805", "profile_link_color": "4A913C", "profile_sidebar_border_color": "000000", "profile_sidebar_fill_color": "000000", "profile_text_color": "000000", "profile_use_background_image": true, "has_extended_profile": false, "default_profile": false, "default_profile_image": false, "following": false, "follow_request_sent": false, "notifications": false, "translator_type": "none"}, "geo": null, "coordinates": null, "place": null, "contributors": null, "is_quote_status": false, "retweet_count": 0, "favorite_count": 0, "favorited": false, "retweeted": false, "lang": "en"}, {"created_at": "Thu Feb 20 16:02:09 +0000 2020", "id": 1230523039470751745, "id_str": "1230523039470751745", "full_text": "RT @blueliv: Threat actors attempt to capitalize on coronavirus outbreak #malware #rat #hash #domain #hashsha256 #malspam #emotet #nanocore…", "truncated": false, "display_text_range": [0, 140], "entities": {"hashtags": [{"text": "malware", "indices": [73, 81]}, {"text": "rat", "indices": [82, 86]}, {"text": "hash", "indices": [87, 92]}, {"text": "domain", "indices": [93, 100]}, {"text": "hashsha256", "indices": [101, 112]}, {"text": "malspam", "indices": [113, 121]}, {"text": "emotet", "indices": [122, 129]}, {"text": "nanocore", "indices": [130, 139]}], "symbols": [], "user_mentions": [{"screen_name": "blueliv", "name": "blueliv", "id": 112458982, "id_str": "112458982", "indices": [3, 11]}], "urls": []}, "metadata": {"iso_language_code": "en", "result_type": "recent"}, "source": "<a href=\"https://mobile.twitter.com\" rel=\"nofollow\">Twitter Web App</a>", "in_reply_to_status_id": null, "in_reply_to_status_id_str": null, "in_reply_to_user_id": null, "in_reply_to_user_id_str": null, "in_reply_to_screen_name": null, "user": {"id": 112458982, "id_str": "112458982", "name": "blueliv", "screen_name": "blueliv", "location": "Barcelona", "description": "We scour the web, the dark web and the deep Internet to empower SOC teams all over the world with advanced cyber threat intel.", "url": "http://t.co/gcAbmmXWH0", "entities": {"url": {"urls": [{"url": "http://t.co/gcAbmmXWH0", "expanded_url": "http://www.blueliv.com/", "display_url": "blueliv.com", "indices": [0, 22]}]}, "description": {"urls": []}}, "protected": false, "followers_count": 2103, "friends_count": 974, "listed_count": 147, "created_at": "Mon Feb 08 15:37:50 +0000 2010", "favourites_count": 709, "utc_offset": null, "time_zone": null, "geo_enabled": true, "verified": false, "statuses_count": 6452, "lang": null, "contributors_enabled": false, "is_translator": false, "is_translation_enabled": false, "profile_background_color": "FFFFFF", "profile_background_image_url": "http://abs.twimg.com/images/themes/theme1/bg.png", "profile_background_image_url_https": "https://abs.twimg.com/images/themes/theme1/bg.png", "profile_background_tile": false, "profile_image_url": "http://pbs.twimg.com/profile_images/1063096167305801728/cp9vX_WD_normal.jpg", "profile_image_url_https": "https://pbs.twimg.com/profile_images/1063096167305801728/cp9vX_WD_normal.jpg", "profile_banner_url": "https://pbs.twimg.com/profile_banners/112458982/1579511741", "profile_link_color": "FF585D", "profile_sidebar_border_color": "FFFFFF", "profile_sidebar_fill_color": "DDEEF6", "profile_text_color": "333333", "profile_use_background_image": false, "has_extended_profile": false, "default_profile": false, "default_profile_image": false, "following": false, "follow_request_sent": false, "notifications": false, "translator_type": "none"}, "geo": null, "coordinates": null, "place": null, "contributors": null, "retweeted_status": {"created_at": "Thu Feb 20 16:00:42 +0000 2020", "id": 1230522675765940226, "id_str": "1230522675765940226", "full_text": "Threat actors attempt to capitalize on coronavirus outbreak #malware #rat #hash #domain #hashsha256 #malspam #emotet #nanocore #coronavirus https://t.co/gcdJoubaxK https://t.co/NaHdZ4vlPb", "truncated": false, "display_text_range": [0, 163], "entities": {"hashtags": [{"text": "malware", "indices": [60, 68]}, {"text": "rat", "indices": [69, 73]}, {"text": "hash", "indices": [74, 79]}, {"text": "domain", "indices": [80, 87]}, {"text": "hashsha256", "indices": [88, 99]}, {"text": "malspam", "indices": [100, 108]}, {"text": "emotet", "indices": [109, 116]}, {"text": "nanocore", "indices": [117, 126]}, {"text": "coronavirus", "indices": [127, 139]}], "symbols": [], "user_mentions": [], "urls": [{"url": "https://t.co/gcdJoubaxK", "expanded_url": "https://community.blueliv.com/#!/s/5e46698382df413eaf339b62", "display_url": "community.blueliv.com/#!/s/5e4669838…", "indices": [140, 163]}], "media": [{"id": 1230522672783773698, "id_str": "1230522672783773698", "indices": [164, 187], "media_url": "http://pbs.twimg.com/media/EROx2e9XUAIq610.jpg", "media_url_https": "https://pbs.twimg.com/media/EROx2e9XUAIq610.jpg", "url": "https://t.co/NaHdZ4vlPb", "display_url": "pic.twitter.com/NaHdZ4vlPb", "expanded_url": "https://twitter.com/blueliv/status/1230522675765940226/photo/1", "type": "photo", "sizes": {"large": {"w": 2048, "h": 1366, "resize": "fit"}, "thumb": {"w": 150, "h": 150, "resize": "crop"}, "small": {"w": 680, "h": 454, "resize": "fit"}, "medium": {"w": 1200, "h": 800, "resize": "fit"}}}]}, "extended_entities": {"media": [{"id": 1230522672783773698, "id_str": "1230522672783773698", "indices": [164, 187], "media_url": "http://pbs.twimg.com/media/EROx2e9XUAIq610.jpg", "media_url_https": "https://pbs.twimg.com/media/EROx2e9XUAIq610.jpg", "url": "https://t.co/NaHdZ4vlPb", "display_url": "pic.twitter.com/NaHdZ4vlPb", "expanded_url": "https://twitter.com/blueliv/status/1230522675765940226/photo/1", "type": "photo", "sizes": {"large": {"w": 2048, "h": 1366, "resize": "fit"}, "thumb": {"w": 150, "h": 150, "resize": "crop"}, "small": {"w": 680, "h": 454, "resize": "fit"}, "medium": {"w": 1200, "h": 800, "resize": "fit"}}}]}, "metadata": {"iso_language_code": "en", "result_type": "recent"}, "source": "<a href=\"https://buffer.com\" rel=\"nofollow\">Buffer</a>", "in_reply_to_status_id": null, "in_reply_to_status_id_str": null, "in_reply_to_user_id": null, "in_reply_to_user_id_str": null, "in_reply_to_screen_name": null, "user": {"id": 112458982, "id_str": "112458982", "name": "blueliv", "screen_name": "blueliv", "location": "Barcelona", "description": "We scour the web, the dark web and the deep Internet to empower SOC teams all over the world with advanced cyber threat intel.", "url": "http://t.co/gcAbmmXWH0", "entities": {"url": {"urls": [{"url": "http://t.co/gcAbmmXWH0", "expanded_url": "http://www.blueliv.com/", "display_url": "blueliv.com", "indices": [0, 22]}]}, "description": {"urls": []}}, "protected": false, "followers_count": 2103, "friends_count": 974, "listed_count": 147, "created_at": "Mon Feb 08 15:37:50 +0000 2010", "favourites_count": 709, "utc_offset": null, "time_zone": null, "geo_enabled": true, "verified": false, "statuses_count": 6452, "lang": null, "contributors_enabled": false, "is_translator": false, "is_translation_enabled": false, "profile_background_color": "FFFFFF", "profile_background_image_url": "http://abs.twimg.com/images/themes/theme1/bg.png", "profile_background_image_url_https": "https://abs.twimg.com/images/themes/theme1/bg.png", "profile_background_tile": false, "profile_image_url": "http://pbs.twimg.com/profile_images/1063096167305801728/cp9vX_WD_normal.jpg", "profile_image_url_https": "https://pbs.twimg.com/profile_images/1063096167305801728/cp9vX_WD_normal.jpg", "profile_banner_url": "https://pbs.twimg.com/profile_banners/112458982/1579511741", "profile_link_color": "FF585D", "profile_sidebar_border_color": "FFFFFF", "profile_sidebar_fill_color": "DDEEF6", "profile_text_color": "333333", "profile_use_background_image": false, "has_extended_profile": false, "default_profile": false, "default_profile_image": false, "following": false, "follow_request_sent": false, "notifications": false, "translator_type": "none"}, "geo": null, "coordinates": null, "place": null, "contributors": null, "is_quote_status": false, "retweet_count": 3, "favorite_count": 0, "favorited": false, "retweeted": false, "possibly_sensitive": false, "lang": "en"}, "is_quote_status": false, "retweet_count": 3, "favorite_count": 0, "favorited": false, "retweeted": false, "lang": "en"}, {"created_at": "Thu Feb 20 16:01:30 +0000 2020", "id": 1230522875138002944, "id_str": "1230522875138002944", "full_text": "RT @blueliv: Threat actors attempt to capitalize on coronavirus outbreak #malware #rat #hash #domain #hashsha256 #malspam #emotet #nanocore…", "truncated": false, "display_text_range": [0, 140], "entities": {"hashtags": [{"text": "malware", "indices": [73, 81]}, {"text": "rat", "indices": [82, 86]}, {"text": "hash", "indices": [87, 92]}, {"text": "domain", "indices": [93, 100]}, {"text": "hashsha256", "indices": [101, 112]}, {"text": "malspam", "indices": [113, 121]}, {"text": "emotet", "indices": [122, 129]}, {"text": "nanocore", "indices": [130, 139]}], "symbols": [], "user_mentions": [{"screen_name": "blueliv", "name": "blueliv", "id": 112458982, "id_str": "112458982", "indices": [3, 11]}], "urls": []}, "metadata": {"iso_language_code": "en", "result_type": "recent"}, "source": "<a href=\"https://homeinc.com\" rel=\"nofollow\">forRetweeting</a>", "in_reply_to_status_id": null, "in_reply_to_status_id_str": null, "in_reply_to_user_id": null, "in_reply_to_user_id_str": null, "in_reply_to_screen_name": null, "user": {"id": 1142424032794406912, "id_str": "1142424032794406912", "name": "Cyber Security News", "screen_name": "CyberSecurityN8", "location": "", "description": "The place for InfoSec, CyberSecurity, DevSecOps, DataSecurity and many more!!! Stay tuned.", "url": null, "entities": {"description": {"urls": []}}, "protected": false, "followers_count": 2410, "friends_count": 1, "listed_count": 61, "created_at": "Sat Jun 22 13:28:09 +0000 2019", "favourites_count": 0, "utc_offset": null, "time_zone": null, "geo_enabled": false, "verified": false, "statuses_count": 123980, "lang": null, "contributors_enabled": false, "is_translator": false, "is_translation_enabled": false, "profile_background_color": "F5F8FA", "profile_background_image_url": null, "profile_background_image_url_https": null, "profile_background_tile": false, "profile_image_url": "http://pbs.twimg.com/profile_images/1197135188473475074/8svI-1EO_normal.jpg", "profile_image_url_https": "https://pbs.twimg.com/profile_images/1197135188473475074/8svI-1EO_normal.jpg", "profile_banner_url": "https://pbs.twimg.com/profile_banners/1142424032794406912/1574254287", "profile_link_color": "1DA1F2", "profile_sidebar_border_color": "C0DEED", "profile_sidebar_fill_color": "DDEEF6", "profile_text_color": "333333", "profile_use_background_image": true, "has_extended_profile": false, "default_profile": true, "default_profile_image": false, "following": false, "follow_request_sent": false, "notifications": false, "translator_type": "none"}, "geo": null, "coordinates": null, "place": null, "contributors": null, "retweeted_status": {"created_at": "Thu Feb 20 16:00:42 +0000 2020", "id": 1230522675765940226, "id_str": "1230522675765940226", "full_text": "Threat actors attempt to capitalize on coronavirus outbreak #malware #rat #hash #domain #hashsha256 #malspam #emotet #nanocore #coronavirus https://t.co/gcdJoubaxK https://t.co/NaHdZ4vlPb", "truncated": false, "display_text_range": [0, 163], "entities": {"hashtags": [{"text": "malware", "indices": [60, 68]}, {"text": "rat", "indices": [69, 73]}, {"text": "hash", "indices": [74, 79]}, {"text": "domain", "indices": [80, 87]}, {"text": "hashsha256", "indices": [88, 99]}, {"text": "malspam", "indices": [100, 108]}, {"text": "emotet", "indices": [109, 116]}, {"text": "nanocore", "indices": [117, 126]}, {"text": "coronavirus", "indices": [127, 139]}], "symbols": [], "user_mentions": [], "urls": [{"url": "https://t.co/gcdJoubaxK", "expanded_url": "https://community.blueliv.com/#!/s/5e46698382df413eaf339b62", "display_url": "community.blueliv.com/#!/s/5e4669838…", "indices": [140, 163]}], "media": [{"id": 1230522672783773698, "id_str": "1230522672783773698", "indices": [164, 187], "media_url": "http://pbs.twimg.com/media/EROx2e9XUAIq610.jpg", "media_url_https": "https://pbs.twimg.com/media/EROx2e9XUAIq610.jpg", "url": "https://t.co/NaHdZ4vlPb", "display_url": "pic.twitter.com/NaHdZ4vlPb", "expanded_url": "https://twitter.com/blueliv/status/1230522675765940226/photo/1", "type": "photo", "sizes": {"large": {"w": 2048, "h": 1366, "resize": "fit"}, "thumb": {"w": 150, "h": 150, "resize": "crop"}, "small": {"w": 680, "h": 454, "resize": "fit"}, "medium": {"w": 1200, "h": 800, "resize": "fit"}}}]}, "extended_entities": {"media": [{"id": 1230522672783773698, "id_str": "1230522672783773698", "indices": [164, 187], "media_url": "http://pbs.twimg.com/media/EROx2e9XUAIq610.jpg", "media_url_https": "https://pbs.twimg.com/media/EROx2e9XUAIq610.jpg", "url": "https://t.co/NaHdZ4vlPb", "display_url": "pic.twitter.com/NaHdZ4vlPb", "expanded_url": "https://twitter.com/blueliv/status/1230522675765940226/photo/1", "type": "photo", "sizes": {"large": {"w": 2048, "h": 1366, "resize": "fit"}, "thumb": {"w": 150, "h": 150, "resize": "crop"}, "small": {"w": 680, "h": 454, "resize": "fit"}, "medium": {"w": 1200, "h": 800, "resize": "fit"}}}]}, "metadata": {"iso_language_code": "en", "result_type": "recent"}, "source": "<a href=\"https://buffer.com\" rel=\"nofollow\">Buffer</a>", "in_reply_to_status_id": null, "in_reply_to_status_id_str": null, "in_reply_to_user_id": null, "in_reply_to_user_id_str": null, "in_reply_to_screen_name": null, "user": {"id": 112458982, "id_str": "112458982", "name": "blueliv", "screen_name": "blueliv", "location": "Barcelona", "description": "We scour the web, the dark web and the deep Internet to empower SOC teams all over the world with advanced cyber threat intel.", "url": "http://t.co/gcAbmmXWH0", "entities": {"url": {"urls": [{"url": "http://t.co/gcAbmmXWH0", "expanded_url": "http://www.blueliv.com/", "display_url": "blueliv.com", "indices": [0, 22]}]}, "description": {"urls": []}}, "protected": false, "followers_count": 2103, "friends_count": 974, "listed_count": 147, "created_at": "Mon Feb 08 15:37:50 +0000 2010", "favourites_count": 709, "utc_offset": null, "time_zone": null, "geo_enabled": true, "verified": false, "statuses_count": 6452, "lang": null, "contributors_enabled": false, "is_translator": false, "is_translation_enabled": false, "profile_background_color": "FFFFFF", "profile_background_image_url": "http://abs.twimg.com/images/themes/theme1/bg.png", "profile_background_image_url_https": "https://abs.twimg.com/images/themes/theme1/bg.png", "profile_background_tile": false, "profile_image_url": "http://pbs.twimg.com/profile_images/1063096167305801728/cp9vX_WD_normal.jpg", "profile_image_url_https": "https://pbs.twimg.com/profile_images/1063096167305801728/cp9vX_WD_normal.jpg", "profile_banner_url": "https://pbs.twimg.com/profile_banners/112458982/1579511741", "profile_link_color": "FF585D", "profile_sidebar_border_color": "FFFFFF", "profile_sidebar_fill_color": "DDEEF6", "profile_text_color": "333333", "profile_use_background_image": false, "has_extended_profile": false, "default_profile": false, "default_profile_image": false, "following": false, "follow_request_sent": false, "notifications": false, "translator_type": "none"}, "geo": null, "coordinates": null, "place": null, "contributors": null, "is_quote_status": false, "retweet_count": 3, "favorite_count": 0, "favorited": false, "retweeted": false, "possibly_sensitive": false, "lang": "en"}, "is_quote_status": false, "retweet_count": 3, "favorite_count": 0, "favorited": false, "retweeted": false, "lang": "en"}, {"created_at": "Thu Feb 20 16:01:28 +0000 2020", "id": 1230522868343169025, "id_str": "1230522868343169025", "full_text": "RT @blueliv: Threat actors attempt to capitalize on coronavirus outbreak #malware #rat #hash #domain #hashsha256 #malspam #emotet #nanocore…", "truncated": false, "display_text_range": [0, 140], "entities": {"hashtags": [{"text": "malware", "indices": [73, 81]}, {"text": "rat", "indices": [82, 86]}, {"text": "hash", "indices": [87, 92]}, {"text": "domain", "indices": [93, 100]}, {"text": "hashsha256", "indices": [101, 112]}, {"text": "malspam", "indices": [113, 121]}, {"text": "emotet", "indices": [122, 129]}, {"text": "nanocore", "indices": [130, 139]}], "symbols": [], "user_mentions": [{"screen_name": "blueliv", "name": "blueliv", "id": 112458982, "id_str": "112458982", "indices": [3, 11]}], "urls": []}, "metadata": {"iso_language_code": "en", "result_type": "recent"}, "source": "<a href=\"https://ho.com\" rel=\"nofollow\">auto is the only way it can be </a>", "in_reply_to_status_id": null, "in_reply_to_status_id_str": null, "in_reply_to_user_id": null, "in_reply_to_user_id_str": null, "in_reply_to_screen_name": null, "user": {"id": 710123736175783938, "id_str": "710123736175783938", "name": "Security Testing", "screen_name": "sectest9", "location": "Hyderabad, India", "description": "News Hub! Get the latest Security News & Updates!", "url": null, "entities": {"description": {"urls": []}}, "protected": false, "followers_count": 29827, "friends_count": 1, "listed_count": 7183, "created_at": "Wed Mar 16 15:21:07 +0000 2016", "favourites_count": 7, "utc_offset": null, "time_zone": null, "geo_enabled": false, "verified": false, "statuses_count": 1703566, "lang": null, "contributors_enabled": false, "is_translator": false, "is_translation_enabled": false, "profile_background_color": "F5F8FA", "profile_background_image_url": null, "profile_background_image_url_https": null, "profile_background_tile": false, "profile_image_url": "http://pbs.twimg.com/profile_images/710735123876982784/GjV7JWMk_normal.jpg", "profile_image_url_https": "https://pbs.twimg.com/profile_images/710735123876982784/GjV7JWMk_normal.jpg", "profile_banner_url": "https://pbs.twimg.com/profile_banners/710123736175783938/1458287472", "profile_link_color": "1DA1F2", "profile_sidebar_border_color": "C0DEED", "profile_sidebar_fill_color": "DDEEF6", "profile_text_color": "333333", "profile_use_background_image": true, "has_extended_profile": false, "default_profile": true, "default_profile_image": false, "following": false, "follow_request_sent": false, "notifications": false, "translator_type": "none"}, "geo": null, "coordinates": null, "place": null, "contributors": null, "retweeted_status": {"created_at": "Thu Feb 20 16:00:42 +0000 2020", "id": 1230522675765940226, "id_str": "1230522675765940226", "full_text": "Threat actors attempt to capitalize on coronavirus outbreak #malware #rat #hash #domain #hashsha256 #malspam #emotet #nanocore #coronavirus https://t.co/gcdJoubaxK https://t.co/NaHdZ4vlPb", "truncated": false, "display_text_range": [0, 163], "entities": {"hashtags": [{"text": "malware", "indices": [60, 68]}, {"text": "rat", "indices": [69, 73]}, {"text": "hash", "indices": [74, 79]}, {"text": "domain", "indices": [80, 87]}, {"text": "hashsha256", "indices": [88, 99]}, {"text": "malspam", "indices": [100, 108]}, {"text": "emotet", "indices": [109, 116]}, {"text": "nanocore", "indices": [117, 126]}, {"text": "coronavirus", "indices": [127, 139]}], "symbols": [], "user_mentions": [], "urls": [{"url": "https://t.co/gcdJoubaxK", "expanded_url": "https://community.blueliv.com/#!/s/5e46698382df413eaf339b62", "display_url": "community.blueliv.com/#!/s/5e4669838…", "indices": [140, 163]}], "media": [{"id": 1230522672783773698, "id_str": "1230522672783773698", "indices": [164, 187], "media_url": "http://pbs.twimg.com/media/EROx2e9XUAIq610.jpg", "media_url_https": "https://pbs.twimg.com/media/EROx2e9XUAIq610.jpg", "url": "https://t.co/NaHdZ4vlPb", "display_url": "pic.twitter.com/NaHdZ4vlPb", "expanded_url": "https://twitter.com/blueliv/status/1230522675765940226/photo/1", "type": "photo", "sizes": {"large": {"w": 2048, "h": 1366, "resize": "fit"}, "thumb": {"w": 150, "h": 150, "resize": "crop"}, "small": {"w": 680, "h": 454, "resize": "fit"}, "medium": {"w": 1200, "h": 800, "resize": "fit"}}}]}, "extended_entities": {"media": [{"id": 1230522672783773698, "id_str": "1230522672783773698", "indices": [164, 187], "media_url": "http://pbs.twimg.com/media/EROx2e9XUAIq610.jpg", "media_url_https": "https://pbs.twimg.com/media/EROx2e9XUAIq610.jpg", "url": "https://t.co/NaHdZ4vlPb", "display_url": "pic.twitter.com/NaHdZ4vlPb", "expanded_url": "https://twitter.com/blueliv/status/1230522675765940226/photo/1", "type": "photo", "sizes": {"large": {"w": 2048, "h": 1366, "resize": "fit"}, "thumb": {"w": 150, "h": 150, "resize": "crop"}, "small": {"w": 680, "h": 454, "resize": "fit"}, "medium": {"w": 1200, "h": 800, "resize": "fit"}}}]}, "metadata": {"iso_language_code": "en", "result_type": "recent"}, "source": "<a href=\"https://buffer.com\" rel=\"nofollow\">Buffer</a>", "in_reply_to_status_id": null, "in_reply_to_status_id_str": null, "in_reply_to_user_id": null, "in_reply_to_user_id_str": null, "in_reply_to_screen_name": null, "user": {"id": 112458982, "id_str": "112458982", "name": "blueliv", "screen_name": "blueliv", "location": "Barcelona", "description": "We scour the web, the dark web and the deep Internet to empower SOC teams all over the world with advanced cyber threat intel.", "url": "http://t.co/gcAbmmXWH0", "entities": {"url": {"urls": [{"url": "http://t.co/gcAbmmXWH0", "expanded_url": "http://www.blueliv.com/", "display_url": "blueliv.com", "indices": [0, 22]}]}, "description": {"urls": []}}, "protected": false, "followers_count": 2103, "friends_count": 974, "listed_count": 147, "created_at": "Mon Feb 08 15:37:50 +0000 2010", "favourites_count": 709, "utc_offset": null, "time_zone": null, "geo_enabled": true, "verified": false, "statuses_count": 6452, "lang": null, "contributors_enabled": false, "is_translator": false, "is_translation_enabled": false, "profile_background_color": "FFFFFF", "profile_background_image_url": "http://abs.twimg.com/images/themes/theme1/bg.png", "profile_background_image_url_https": "https://abs.twimg.com/images/themes/theme1/bg.png", "profile_background_tile": false, "profile_image_url": "http://pbs.twimg.com/profile_images/1063096167305801728/cp9vX_WD_normal.jpg", "profile_image_url_https": "https://pbs.twimg.com/profile_images/1063096167305801728/cp9vX_WD_normal.jpg", "profile_banner_url": "https://pbs.twimg.com/profile_banners/112458982/1579511741", "profile_link_color": "FF585D", "profile_sidebar_border_color": "FFFFFF", "profile_sidebar_fill_color": "DDEEF6", "profile_text_color": "333333", "profile_use_background_image": false, "has_extended_profile": false, "default_profile": false, "default_profile_image": false, "following": false, "follow_request_sent": false, "notifications": false, "translator_type": "none"}, "geo": null, "coordinates": null, "place": null, "contributors": null, "is_quote_status": false, "retweet_count": 3, "favorite_count": 0, "favorited": false, "retweeted": false, "possibly_sensitive": false, "lang": "en"}, "is_quote_status": false, "retweet_count": 3, "favorite_count": 0, "favorited": false, "retweeted": false, "lang": "en"}], "search_metadata": {"completed_in": 0.052, "max_id": 1231968185655496704, "max_id_str": "1231968185655496704", "next_results": "?max_id=1230522868343169024&q=%23NanoCore&lang=en&include_entities=1", "query": "%23NanoCore", "refresh_url": "?since_id=1231968185655496704&q=%23NanoCore&lang=en&include_entities=1", "count": 15, "since_id": 0, "since_id_str": "0"}}